streamlit_echarts/__init__.py
streamlit_echarts/frontend/build/asset-manifest.json
streamlit_echarts/frontend/build/index.html
streamlit_echarts/frontend/build/precache-manifest.c770dee05c0c542ac4acd3eccfd9de14.js
streamlit_echarts/frontend/build/service-worker.js
streamlit_echarts/frontend/build/static/css/main.d984dddf.chunk.css
streamlit_echarts/frontend/build/static/css/main.d984dddf.chunk.css.map
streamlit_echarts/frontend/build/static/js/2.25653e77.chunk.js
streamlit_echarts/frontend/build/static/js/2.25653e77.chunk.js.LICENSE.txt
streamlit_echarts/frontend/build/static/js/2.25653e77.chunk.js.map
streamlit_echarts/frontend/build/static/js/main.2e4d195b.chunk.js
streamlit_echarts/frontend/build/static/js/main.2e4d195b.chunk.js.map
streamlit_echarts/frontend/build/static/js/runtime-main.34185f1e.js
streamlit_echarts/frontend/build/static/js/runtime-main.34185f1e.js.map
streamlit_echarts-0.4.0.dist-info/LICENSE
streamlit_echarts-0.4.0.dist-info/METADATA
streamlit_echarts-0.4.0.dist-info/WHEEL
streamlit_echarts-0.4.0.dist-info/top_level.txt
streamlit_echarts-0.4.0.dist-info/RECORD
