Metadata-Version: 2.1
Name: streamlit-echarts
Version: 0.4.0
Summary: Echarts custom component for Streamlit
Home-page: https://github.com/andfanilo/streamlit-echarts
Author: Fanilo ANDRIANASOLO
Author-email: andfanilo@gmail.com
License: UNKNOWN
Platform: UNKNOWN
Requires-Python: >=3.6
